[
  {
    "zipCode": "10001",
    "borough": "Manhattan",
    "noiseCount": 8765,
    "rodentCount": 4321,
    "totalComplaints": 13086
  },
  {
    "zipCode": "11201",
    "borough": "Brooklyn",
    "noiseCount": 7654,
    "rodentCount": 5432,
    "totalComplaints": 13086
  },
  {
    "zipCode": "10003",
    "borough": "Manhattan",
    "noiseCount": 9876,
    "rodentCount": 3210,
    "totalComplaints": 13086
  },
  {
    "zipCode": "11211",
    "borough": "Brooklyn",
    "noiseCount": 6543,
    "rodentCount": 4567,
    "totalComplaints": 11110
  },
  {
    "zipCode": "11101",
    "borough": "Queens",
    "noiseCount": 5678,
    "rodentCount": 3456,
    "totalComplaints": 9134
  }
]
